pyfarmer/__init__.py
pyfarmer/_pyfarmer.py
pyfarmer/_strategies.py
pyfarmer/_utils.py
pyfarmer/py.typed
pyfarmer-2.0.1.dist-info/LICENSE
pyfarmer-2.0.1.dist-info/METADATA
pyfarmer-2.0.1.dist-info/WHEEL
pyfarmer-2.0.1.dist-info/RECORD
